{"glosses":[[1,{"ori":["nawkisaalru","amiamiaku","ku","lrabusu."],"gloss":[["naw=kisaalru","1S.BN=borrow","第一人稱單數.附著主格=借"],["a-iya-iya=aku","RLS-say-RED=1S.BN","實現-說-重疊=第一人稱單數.附著主格"],["ku","OBL","斜格"],["lrabu=su.","knife=2S.BG","刀=第二人稱單數.附著屬格"]],"free":["#e I want to borrow your knife.","#c 我想借你的刀。(lit: 我的心(想)借你的刀)"],"s_end":true,"iu_a_span":[null,null],"meta":{"type":"Sentence","language":"霧台魯凱語, Rukai, Budai","speaker":"麥長老, Baelrece, M, 1958","collected":"2020-05-28"}}],[2,{"ori":["lrikisaalruaku","ku","lrabusu."],"gloss":[["lri-kisaalru=aku","FUT-borrow=1S.BN","未來式-借=第一人稱單數.附著主格"],["ku","OBL","斜格"],["lrabu=su.","knife=2S.BG","刀=第二人稱單數.附著屬格"]],"free":["#e I will borrow your knife.","#c 我要借你的刀。"],"s_end":true,"iu_a_span":[null,null],"meta":{"type":"Sentence","language":"霧台魯凱語, Rukai, Budai","speaker":"麥長老, Baelrece, M, 1958","collected":"2020-05-28"}}],[3,{"ori":["ku","ama","malrigili","alupu."],"gloss":[["ku","NOM","主格"],["ama","father","爸爸"],["ma-lrigili","STAT.RLS-be.smart","狀態.實現-聰明"],["alupu.","hunt","打獵"]],"free":["#e My father is good at hunting.","#c 我爸爸很會打獵。"],"s_end":true,"iu_a_span":[null,null],"meta":{"type":"Sentence","language":"霧台魯凱語, Rukai, Budai","speaker":"麥長老, Baelrece, M, 1958","collected":"2020-05-28"}}],[4,{"ori":["kay","Kui","magilrimucu","si","la","katuase","kiaangatu."],"gloss":[["kay","this","這"],["Kui","Kui","Kui"],["ma-gilrimucu","STAT.RLS-be.mad","狀態.實現-生氣"],["si","and","和"],["la","then","然後"],["ka-tuase","STAT.IRR-leave","狀態.非實現-離開"],["ki-a-angatu.","PASS-RLS-tree","被動-實現-樹"]],"free":["#e Kui was mad and went to chop the wood.","#c Kui 很生氣然後就去砍柴了。"],"s_end":true,"iu_a_span":[null,null],"meta":{"type":"Sentence","language":"霧台魯凱語, Rukai, Budai","speaker":"麥長老, Baelrece, M, 1958","collected":"2020-05-28"}}],[5,{"ori":["kiararagay","kay","takivavange","ki","Muni."],"gloss":[["ki-<a>-<ra>ragay","<RLS>-<RED>be.happy","<實現>-<重疊>快樂"],["kay","this","這"],["ta-kivavange","LOC-play","處所-玩"],["ki","OBL","斜格"],["Muni.","Muni","Muni"]],"free":["#e Muni played happily.","#c Muni 玩得很快樂。"],"s_end":true,"iu_a_span":[null,null],"meta":{"type":"Sentence","language":"霧台魯凱語, Rukai, Budai","speaker":"麥長老, Baelrece, M, 1958","collected":"2020-05-28"}}],[6,{"ori":["kiararakay","kay","takivavangane","kay","Muni."],"gloss":[["ki-<a>-<ra>ragay","<RLS>-<RED>be.happy","<實現>-<重疊>快樂"],["kay","this","這"],["ta-kivavange-ane","LOC","處所-play-名物化"],["kay","-play-NMLZ","這"],["Muni.","this","Muni"]],"free":["#e Muni played happily.","#c Muni 玩得很快樂。"],"s_end":true,"iu_a_span":[null,null],"meta":{"type":"Sentence","language":"霧台魯凱語, Rukai, Budai","speaker":"麥長老, Baelrece, M, 1958","collected":"2020-05-28"}}],[7,{"ori":["malrigi/maelreelrenge/maadraw","kay","Laucu."],"gloss":[["ma-lrigi/ma-elre-elrenge/ma-adraw","STAT.RLS-be.smart/STAT.RLS-RED-be.tall/STAT.RLS-be.big","狀態.實現.聰明/狀態.實現-重疊-高/狀態.實現-大"],["kay","this","這"],["Laucu.","Laucu","Laucu"]],"free":["#e Laucu is smart/tall/big.","#c Laucu很聰明/高/大。"],"s_end":true,"iu_a_span":[null,null],"meta":{"type":"Sentence","language":"霧台魯凱語, Rukai, Budai","speaker":"麥長老, Baelrece, M, 1958","collected":"2020-05-28"}}],[8,{"ori":["arwakaelrenge","kay","icaily","kay","Laucu."],"gloss":[["aru-a-ka-elrenge","be.getting-STAT.IRR-be.tall","越來越-狀態.非實現-高"],["kay","this","這"],["i-cayli","LOC-year","處所-年"],["kay","this","這"],["Laucu.","Laucu","Laucu"]],"free":["#e Laucu grew tall this year.","#c Laucu今年長很高。"],"s_end":true,"iu_a_span":[null,null],"meta":{"type":"Sentence","language":"霧台魯凱語, Rukai, Budai","speaker":"麥長老, Baelrece, M, 1958","collected":"2020-05-28"}}],[9,{"ori":["maridare","kaadraw","kay","Laucu."],"gloss":[["ma-ridare","STAT.RLS-be.fast","狀態.實現-快"],["ka-adraw","STAT.IRR-be.big","狀態.非實現-大"],["kay","this","這"],["Laucu.","Laucu","Laucu"]],"free":["#e Laucu grew tall fast.","#c Laucu 長得很快。"],"s_end":true,"iu_a_span":[null,null],"meta":{"type":"Sentence","language":"霧台魯凱語, Rukai, Budai","speaker":"麥長老, Baelrece, M, 1958","collected":"2020-05-28"}}],[10,{"ori":["maridare","ku","icaili","kaadraw","kay","Laucu."],"gloss":[["ma-ridare","STAT.RLS-be.fast","狀態.實現-快"],["ku","OBL","斜格"],["icaili","year","去年"],["ka-adraw","STAT.IRR-be.big","狀態.非實現-大"],["kay","this","這"],["Laucu","Laucu","Laucu"]],"free":["#e Laucu grew tall fast last year","#c Laucu 去年長很快。"],"s_end":true,"iu_a_span":[null,null],"meta":{"type":"Sentence","language":"霧台魯凱語, Rukai, Budai","speaker":"麥長老, Baelrece, M, 1958","collected":"2020-05-28"}}],[11,{"ori":["kiapakilringaw","kay","takacaemane","kay","Laucu."],"gloss":[["ki-a-pakilringaw","get-RLS-serious","變得-實現-嚴重"],["kay","this","這"],["ta-ka-caeme-ane","LOC-STAT.IRR-be.sick-NMLZ","處所-狀態.非現實-生病-名物化"],["kay","this","這"],["Laucu.","Laucu","Laucu"]],"free":["#e Laucu is sick seriously.","#c Laucu 病得很重。"],"s_end":true,"iu_a_span":[null,null],"meta":{"type":"Sentence","language":"霧台魯凱語, Rukai, Budai","speaker":"麥長老, Baelrece, M, 1958","collected":"2020-05-28"}}],[12,{"ori":["kiapakilringaw","kacaeme","kay","Laucu."],"gloss":[["Ki-a-pakilringaw","get-RLS-serious","變得-實現-嚴重"],["ka-caeme","STAT.IRR-be.sick","狀態.非現實-生病"],["kay","this","這"],["Laucu.","Laucu","Laucu"]],"free":["#e Laucu is sick seriously.","#c Laucu 病得很重。"],"s_end":true,"iu_a_span":[null,null],"meta":{"type":"Sentence","language":"霧台魯凱語, Rukai, Budai","speaker":"麥長老, Baelrece, M, 1958","collected":"2020-05-28"}}],[13,{"ori":["kiapakilringaw","kadula","kay","Laucu."],"gloss":[["ki-a-pakilringaw","get-RLS-be.serious","變得-實現-嚴重"],["ka-dula","STAT.IRR-be.hurt","狀態.非現實-受傷"],["kay","this","這"],["Laucu.","Laucu","Laucu"]],"free":["#e Laucu is hurt seriously.","#c Laucu 傷得很重。"],"s_end":true,"iu_a_span":[null,null],"meta":{"type":"Sentence","language":"霧台魯凱語, Rukai, Budai","speaker":"麥長老, Baelrece, M, 1958","collected":"2020-05-28"}}],[14,{"ori":["luiya","alawlriudale."],"gloss":[["luiya","tomorrow","明天"],["a-law-lri-udale.","A-POSS.MOD-FUT-rain","A-可能.情態-未來式-下雨"]],"free":["#e It will probably rain tomorrow.","#c 明天可能會下雨。"],"s_end":true,"iu_a_span":[null,null],"meta":{"type":"Sentence","language":"霧台魯凱語, Rukai, Budai","speaker":"麥長老, Baelrece, M, 1958","collected":"2020-05-28"}}],[15,{"ori":["alau","lrimuTaihukaku","luiya."],"gloss":[["alau","maybe","可能"],["lri-mu-Taihuku-aku","FUT-go-Taipei-1S.BN","未來式-去-台北"],["luiya.","tomorrow","明天"]],"free":["#e I may go to Taipei tomorrow.","#c 我明天可能會去台北。"],"s_end":true,"iu_a_span":[null,null],"meta":{"type":"Sentence","language":"霧台魯凱語, Rukai, Budai","speaker":"麥長老, Baelrece, M, 1958","collected":"2020-05-28"}}],[16,{"ori":["alau","lrikatuasaku","luiya","muTaihuku."],"gloss":[["alau","maybe","可能"],["lri-ka-tuase=aku.","FUT-STAT.IRR-leave=1S.BN","未來-離開=第一人稱單數.附著主格"],["luiya","tomorrow","明天"],["mu-Taihuku","go-Taipei","去-台北"]],"free":["#e I may leave for Taipei.","#c 我明天可能會(離開)去台北。"],"s_end":true,"iu_a_span":[null,null],"meta":{"type":"Sentence","language":"霧台魯凱語, Rukai, Budai","speaker":"麥長老, Baelrece, M, 1958","collected":"2020-05-28"}}],[17,{"ori":["alau","lrika","tuasaku","muTaihuku","luiya."],"gloss":[["alau","a-POSS.MOD","a-可能.情態"],["lri-ka-tuase=aku","FUT-STAT.IRR-leave=1S.BN","未來式-狀態.非實現-離開=第一人稱單數.附著主格"],["mu-Taihuku","go-Taipei","去-台北"],["luiya.","tomorrow","明天"]],"free":["#e I may leave for for Taipei.","#c 我明天可能會(離開)去台北。"],"s_end":true,"iu_a_span":[null,null],"meta":{"type":"Sentence","language":"霧台魯凱語, Rukai, Budai","speaker":"麥長老, Baelrece, M, 1958","collected":"2020-05-28"}}],[18,{"ori":["kay","vavalake","makupaupa."],"gloss":[["kay","this","這"],["vavalake","kid","小孩"],["ma-kupa-upa.","STAT.RLS-steal-RED","狀態.實現-偷-重疊"]],"free":["#e This kid often steals things.","#c 這小孩很常偷東西。"],"s_end":true,"iu_a_span":[null,null],"meta":{"type":"Sentence","language":"霧台魯凱語, Rukai, Budai","speaker":"麥長老, Baelrece, M, 1958","collected":"2020-05-28"}}],[19,{"ori":["kay","lalake","waupa."],"gloss":[["kay","this","這"],["lalake","kid","小孩"],["<w><a>upa.","<ACT><RLS>-steal","<主動>-<實現>-偷"]],"free":["#e This kid stole things.","#c 這小孩偷東西。"],"s_end":true,"iu_a_span":[null,null],"meta":{"type":"Sentence","language":"霧台魯凱語, Rukai, Budai","speaker":"麥長老, Baelrece, M, 1958","collected":"2020-05-28"}}],[20,{"ori":["lu","icaily","isadalranaku","muTaihuku."],"gloss":[["lu","when","當"],["i-cayli","LOC-year","處所-年"],["i-sadalran-aku","often","常常"],["muTaihuku.","go-Taipei","去-台北"]],"free":["#e I will often go to Taipei next year.","#c明年我常常會去臺北。"],"s_end":true,"iu_a_span":[null,null],"meta":{"type":"Sentence","language":"霧台魯凱語, Rukai, Budai","speaker":"麥長老, Baelrece, M, 1958","collected":"2020-05-28"}}],[21,{"ori":["kiangeangaku","kay","barange."],"gloss":[["ki-angeange=aku","get-be.hurt=1S.BG","變得-痛=第一人稱單數.附著主格"],["kay","this","這"],["barange.","stomach","肚子"]],"free":["#e My stomach hurts.","#c我肚子痛。"],"s_end":true,"iu_a_span":[null,null],"meta":{"type":"Sentence","language":"霧台魯凱語, Rukai, Budai","speaker":"麥長老, Baelrece, M, 1958","collected":"2020-05-28"}}],[22,{"ori":["kiarimuaku","kiangeange","kay","barange."],"gloss":[["ki-a-rimu=aku","get-sudden=1S.BG","變得-突然=第一人稱單數.附著主格"],["ki-angeange","get-be.hurt","變得-痛"],["kay","this","這"],["barange.","stomach","肚子"]],"free":["#e My stomach hurt suddently.","#c 我肚子突然很痛"],"s_end":true,"iu_a_span":[null,null],"meta":{"type":"Sentence","language":"霧台魯凱語, Rukai, Budai","speaker":"麥長老, Baelrece, M, 1958","collected":"2020-05-28"}}],[23,{"ori":["kiarimuaku","kidulru."],"gloss":[["ki-a-rimu=aku","get-sudden=1S.BG","變得-突然=第一人稱單數.附著主格"],["ki-dulru.","get-tired","變得-累"]],"free":["#e I got tired suddenly.","#c 我突然很累"],"s_end":true,"iu_a_span":[null,null],"meta":{"type":"Sentence","language":"霧台魯凱語, Rukai, Budai","speaker":"麥長老, Baelrece, M, 1958","collected":"2020-05-28"}}],[24,{"ori":["sa","ka","mwalringedele,","iasadra","ku","udale."],"gloss":[["sa","when","當"],["ka","KA","KA"],["Mwalringedele","noon","中午"],["i<a>sadra","<RLS>-rest","<實現>-休息"],["ku","OBL","斜格"],["udale.","rain","下雨"]],"free":["#e (At) noon, the rain stopped.","#c 中午時，雨停了"],"s_end":true,"iu_a_span":[null,null],"meta":{"type":"Sentence","language":"霧台魯凱語, Rukai, Budai","speaker":"麥長老, Baelrece, M, 1958","collected":"2020-05-28"}}],[25,{"ori":["luiyanga","lrisadra","kay","udale."],"gloss":[["luiya-nga","Tomorrow-PFV","昨天-完成貌"],["lri-sadra","FUT-rest","未來式-休息"],["kay","this","這"],["udale.","rain","雨"]],"free":["#e The rain will stop tomorrow.","#c 雨明天才會停"],"s_end":true,"iu_a_span":[null,null],"meta":{"type":"Sentence","language":"霧台魯凱語, Rukai, Budai","speaker":"麥長老, Baelrece, M, 1958","collected":"2020-05-28"}}],[26,{"ori":["kiapakilringaw","kay","takadulane","kay","Laucu."],"gloss":[["ki-a-pakilringaw","get-RLS-be.serious","變得-實現-嚴重"],["kay","this","這"],["ta-ka-dula-ane","LOC-STAT.IRR-be.hurt-NMLZ","處所-狀態-非實現-受傷-名物化"],["kay","this","這"],["Laucu.","Laucu","Laucu"]],"free":["#e Laucu is hurt seriously.","#c Laucu傷得很重。"],"s_end":true,"iu_a_span":[null,null],"meta":{"type":"Sentence","language":"霧台魯凱語, Rukai, Budai","speaker":"麥長老, Baelrece, M, 1958","collected":"2020-05-28"}}]],"meta":{"type":"Sentence","language":"霧台魯凱語, Rukai, Budai","speaker":"麥長老, Baelrece, M, 1958","collected":"2020-05-28"}}