{"glosses":[[1,{"ori":[],"gloss":[["maisna-sian","from-LOC.MED","從-處格.中距"],["naiia","3PL.NOM","3PL.主格"],["sia","LOC","處格"],["Takau","PN","地名"],["m-insuma.","AF-come","主焦-來"]],"free":["#e They comes from Kaohsiung.","#c 他們從高雄來。","#n maisna-sian naia Takau minsuma.","#n sima maisna-sia Takau 誰從高雄（來）？","#n sima maisna-Takau 是誰從高雄（來）？","#n sima tacini maisna-sia takau minsuma 哪一個人從高雄來？"],"s_end":true,"iu_a_span":[null,null],"meta":{"type":"Sentence","language":"郡群布農語, Bunun, Isbukun","speaker":"顏〇〇, 1958","collected":"2016-06-02"}}],[2,{"ori":[],"gloss":[["tacini","one.CLA.HUM","一.人量詞"],["bunun=a","people=DIST.NOM","人=遠距.主格"],["hai","TOP","主題"],["maisna-sia","from-LOC","從-處格"],["Takau","PN","地名"],["m-insuma.\\","AF-come","主焦.來"]],"free":["#e That person comes from Kaohsiung.","#c 那一個人從高雄來。","#n tacini bunun=an hai maisna-sia Takau minsuma 這一個人是從高雄來的。（附近），同樣的=an 可以用andii（近）和adii（遠）再進一步區分","#n tacini bunun=in hai maisna-sia Takau minsuma 這一個人從高雄來。（靠近話者），不特別指是誰，但是講的話就知道是旁邊的那個了。"],"s_end":true,"iu_a_span":[null,null],"meta":{"type":"Sentence","language":"郡群布農語, Bunun, Isbukun","speaker":"顏〇〇, 1958","collected":"2016-06-02"}}],[3,{"ori":[],"gloss":[["naiia","3PL.NOM","3PL.主格"],["hai","TOP","主題"],["maisna-Takau","from-PN","從-地名"],["ku-ngadah=tan.","go-inside=MED.OBL","去-裡面=中距.斜格"]],"free":["#e They come here from Kaohsiung.","#c 他們從高雄進（來）這裡。","#n ?maisna-sain=cia Takau m-insuma 從高雄（出／回）來","#n *maisna-sain=cia Takau ku-Taihuku 不好，會搞不清楚到底是哪裡","#n maisna-sian=ik sia Takau m-insuma 這句最完整，我從高雄來","#n maisna-sia Takau ku-Taihuku 從高雄到臺北","#n naiia hai maisna-Takau ku-ngadah=cin 他們從高雄進（來）（這裡） 中（靠近speaker","#n naiia hai maisna-Takau ku-ngadah=cia 他們從高雄進（來）（那裡） 遠","#n Talum老師覺得tan是比cin近的（老師是hearer）","#n Hanaivaz 覺得感覺是差不多近的"],"s_end":true,"iu_a_span":[null,null],"meta":{"type":"Sentence","language":"郡群布農語, Bunun, Isbukun","speaker":"顏〇〇, 1958","collected":"2016-06-02"}}],[4,{"ori":[],"gloss":[["naiia","3PL.NOM","3PL.主格"],["hai","TOP","主題"],["maisna-sain=cin","from-LOC.PROX=PROX.OBL","從-處格.近距=近距.斜格"],["ku-Takau.","go-PN","去-地名"]],"free":["#e They are going to Kaohsiung from this (place).","#c 他們從這（去）到高雄。","#n naiia hai maisna-sain=cin ku-Takau minsuma 他們從這到高雄，（又）回來","#n maisna-sain=cin sia Takau minsuma 從高雄到這邊來（sain是指後面的高雄）","#n maisna-sain=cin ku-Takau 從這到高雄","#n sima maisna-sain=cin ku-Takau 誰從這到高雄？"],"s_end":true,"iu_a_span":[null,null],"meta":{"type":"Sentence","language":"郡群布農語, Bunun, Isbukun","speaker":"顏〇〇, 1958","collected":"2016-06-02"}}],[5,{"ori":[],"gloss":[["sima","who","誰"],["bunun","people","人"],["a","LNK","連繫詞"],["tacini=a","one.CLA.HUM=DIST.NOM","一.人量詞=遠距.主格"],["maisna-sain=cin","from-LOC.PROX=PROX.OBL","從-處格.近距=近距.斜格"],["ku-Takau.","go-PN","去-地名"]],"free":["#e Which person goes from here to Kaohsiung?","#c 哪一個人從這裡到高雄？","#n 這個句子有兩個a，第一個a有點像是linker的感覺，和tu有點像，第二個a就是主詞標記"],"s_end":true,"iu_a_span":[null,null],"meta":{"type":"Sentence","language":"郡群布農語, Bunun, Isbukun","speaker":"顏〇〇, 1958","collected":"2016-06-02"}}],[6,{"ori":[],"gloss":[["maisna-sian=im","from-LOC.MED=1EPL.NOM","從-處格.中距=1EPL.主格"],["sia","LOC","LOC"],["Taihuku=cia","PN=DIST.OBL","地名=遠距.斜格"],["ku-sia","go-LOC","去-處格"],["Takau=cin.","PN=PROX.OBL","地名=近距.斜格"]],"free":["#e We are going from Taipei to Kaohsiung.","#c 我們從臺北那裡到高雄這。","#n 前面的 sain 是 deictic dempnstrative, cataphorically point to the place mentioned later.其實已經語法化了，sian本身指示意義已經失去了。","#n Maisna-sain=cia=im sia Taihuku=cia ku-sain=cin Takau=cin. （完整指示地方的說法）我們從那個臺北那裡到這個高雄這裡。"],"s_end":true,"iu_a_span":[null,null],"meta":{"type":"Sentence","language":"郡群布農語, Bunun, Isbukun","speaker":"顏〇〇, 1958","collected":"2016-06-02"}}],[7,{"ori":[],"gloss":[["sai-ciin","LOC-PROX.OBL","處格-近距.斜格"],["tu","LNK","連繫詞"],["siasiing","<L2JphotoL2J>","照片"],["mais","COND","條件詞"],["sadu-an","see-LF","看-處焦"],["hai","TOP","主題"],["cin-liskin","sudden-think","突然-思考"],["mas","OBL","斜格"],["nas-Subali.","the.deceased-PN","已故的-人名"]],"free":["#e Upon seeing this photo, (I) think of the deceased Subali.","#c 這個相片，看的話會想起已故的Subali。","#n saicia tu siasin mais saduan hai cinliskin mas nas-subali? 那個相片","#n saitan tu siasin mais saduan hai cinliskin mas nas-subali? 你那個相片"],"s_end":true,"iu_a_span":[null,null],"meta":{"type":"Sentence","language":"郡群布農語, Bunun, Isbukun","speaker":"顏〇〇, 1958","collected":"2016-06-02"}}]],"meta":{"type":"Sentence","language":"郡群布農語, Bunun, Isbukun","speaker":"顏〇〇, 1958","collected":"2016-06-02"}}