{"glosses":[[1,{"ori":[],"gloss":[["Subali","PN","人名"],["sanavan","night","晚上"],["hai","TOP","主題"],["na=mahtu","IRR=be.able.to","非實現=能夠"],["m-indangaz=ku","AF-help=1SG.GEN","主焦-幫忙=1SG.屬格"],["ma-pa-kaun","AF-CAU-eat","主焦-使役-吃"],["mas","OBL","斜格"],["asu.\\","dog","狗"]],"free":["#e Subali can help me feed my dog tonight.","#c Subali晚上將可以幫我餵狗。","#n mapa-kaun mas asu 可以縮寫成mapa-kaun=s asu"],"s_end":true,"iu_a_span":[null,null],"meta":{"type":"Sentence","language":"郡群布農語, Bunun, Isbukun","speaker":"顏有利, Ciang Ispalida, Male, 1944","collected":"2016-06-05","revised":"2016-06-08"}}],[2,{"ori":[],"gloss":[["saia","3SG.NOM","3SG.主格"],["hai","TOP","主題"],["nau","originally","本來"],["tu","COMP","補語詞"],["na=ma-p-in-kailas","IRR=AF-CAU-become=sparkle","非實現=主焦-使役-變成-生氣勃勃"],["naicia.\\","3PL.GEN","3PL.屬格"]],"free":["#e He originally was going to wake them up.","#c 他本來就要叫他們起床(有責任)。"],"s_end":true,"iu_a_span":[null,null],"meta":{"type":"Sentence","language":"郡群布農語, Bunun, Isbukun","speaker":"顏有利, Ciang Ispalida, Male, 1944","collected":"2016-06-05","revised":"2016-06-08"}}],[3,{"ori":[],"gloss":[["saia","3SG.NOM","3SG.主格"],["hai","TOP","主題"],["asa","want","想要"],["tu","COMP","補語詞"],["ma-p-in-kailas","AF-CAU-become=sparkle","主焦-使役-變成-生氣勃勃"],["naicia.\\","3PL.GEN","3PL.屬格"]],"free":["#e He has to wake them up.","#c 他一定要叫他們起床。","#n asa tu 一定要"],"s_end":true,"iu_a_span":[null,null],"meta":{"type":"Sentence","language":"郡群布農語, Bunun, Isbukun","speaker":"顏有利, Ciang Ispalida, Male, 1944","collected":"2016-06-05","revised":"2016-06-08"}}],[4,{"ori":[],"gloss":[["cis'uni","for","為了"],["mas","OBL","斜格"],["talpataz-un","busy-PF","繁忙-受焦"],["at","then","然後"],["(nau","(originally","(本來"],["tu)","COMP)","補語詞)"],["asa","want","想要"],["Subali","PN","人名"],["tu","COMP","補語詞"],["kuzakuza.\\","work","工作"]],"free":["#e Because Subali is too busy, he has to work.","#c 因為太忙碌, Subali必須上班。","#n nau tu可以省略, asa絕對不可省略。這邊的 nau tu 不是本來的意思了。talpataz-un 強調非常繁忙"],"s_end":true,"iu_a_span":[null,null],"meta":{"type":"Sentence","language":"郡群布農語, Bunun, Isbukun","speaker":"顏有利, Ciang Ispalida, Male, 1944","collected":"2016-06-05","revised":"2016-06-08"}}],[5,{"ori":[],"gloss":[["nau","originally","本來"],["tu","COMP","補語詞"],["(na=)ma-klang","(IRR=)AF-hot","(非實現=)主焦-熱"],["i-nata.\\","be.at-outer.space","處格=外面"]],"free":["#e It must be hot outside.","#c 外面一定很熱；外面本來就很熱","#n maklang-daingaz 特別熱。Daingaz 非常。Ma-daingaz 老人。省略 irrealis na= 意思為「隨口說說」，不強調預測的天氣狀況"],"s_end":true,"iu_a_span":[null,null],"meta":{"type":"Sentence","language":"郡群布農語, Bunun, Isbukun","speaker":"顏有利, Ciang Ispalida, Male, 1944","collected":"2016-06-05","revised":"2016-06-08"}}],[6,{"ori":[],"gloss":[["nau","originally","本來"],["tu","COMP","補語詞"],["na=asa","IRR=want","非實現=想要"],["saia","3SG.NOM","3SG.主格"],["tu","COMP","補語詞"],["m-insuma","AF-come","主焦-來"],["ku-sia","go-LOC","去-處格"],["Kalavuung.\\","PN","地名"]],"free":["#e He should come to Kalavuung.","#c 他應該要來Kalavuung。","#n asa tu 才有一定、應該的意思"],"s_end":true,"iu_a_span":[null,null],"meta":{"type":"Sentence","language":"郡群布農語, Bunun, Isbukun","speaker":"顏有利, Ciang Ispalida, Male, 1944","collected":"2016-06-05","revised":"2016-06-08"}}],[7,{"ori":[],"gloss":[["nau","originally","本來"],["saia","3SG.NOM","3SG.主格"],["tu","COMP","補語詞"],["na=asa","IRR=want","非實現=想要"],["ku-sia","go-LOC","去-處格"],["Kalavung.\\","PN","地名"]],"free":["#e He originally wanted to go to Kalavung.","#c 他本來就想去Kalavung。","#n main verb 為 asa"],"s_end":true,"iu_a_span":[null,null],"meta":{"type":"Sentence","language":"郡群布農語, Bunun, Isbukun","speaker":"顏有利, Ciang Ispalida, Male, 1944","collected":"2016-06-05","revised":"2016-06-08"}}],[8,{"ori":[],"gloss":[["nau","originally","本來"],["saia","3SG.NOM","3SG.主格"],["tu","COMP","補語詞"],["na=asa","IRR=want","非實現=想要"],["tu","COMP","補語詞"],["m-insuma","AF-come","主焦-來"],["ku-sia","go-LOC","去-處格"],["kalavung.\\","PN","地名"]],"free":["#e He will definitely come back to Kalavung.","#c 他一定會回來Kalavung。","#n main verb 為minsuma?"],"s_end":true,"iu_a_span":[null,null],"meta":{"type":"Sentence","language":"郡群布農語, Bunun, Isbukun","speaker":"顏有利, Ciang Ispalida, Male, 1944","collected":"2016-06-05","revised":"2016-06-08"}}]],"meta":{"type":"Sentence","language":"郡群布農語, Bunun, Isbukun","speaker":"顏有利, Ciang Ispalida, Male, 1944","collected":"2016-06-05","revised":"2016-06-08"}}