{"glosses":[[1,{"ori":["Sense","ka","Dakis."],"gloss":[["sense","",""],["ka","",""],["Dakis","",""]],"free":["#c Dakis是老師。","#n 《賽德克語語法概論》 第十章　否定句結構"],"s_end":true,"iu_a_span":[null,null],"meta":{"type":"GrammarBook","topic":"第十章 否定句結構","language":"賽德克語, Seediq, Tgdaya"},"audio_url":"http://ilrdc.tw/grammar/sound/5/10-1-1.mp3"}],[2,{"ori":["Uxe","sense","ka","Dakis."],"gloss":[["uxe","",""],["sense","",""],["ka","",""],["Dakis","",""]],"free":["#c Dakis不是老師。","#n 《賽德克語語法概論》 第十章　否定句結構"],"s_end":true,"iu_a_span":[null,null],"meta":{"type":"GrammarBook","topic":"第十章 否定句結構","language":"賽德克語, Seediq, Tgdaya"},"audio_url":"http://ilrdc.tw/grammar/sound/5/10-1-2.mp3"}],[3,{"ori":["Uxe","mpquyux","ka","kusun."],"gloss":[["uxe","",""],["m-p-quyux","",""],["ka","",""],["kusun","",""]],"free":["#c 明天不會下雨。","#n 《賽德克語語法概論》 第十章　否定句結構"],"s_end":true,"iu_a_span":[null,null],"meta":{"type":"GrammarBook","topic":"第十章 否定句結構","language":"賽德克語, Seediq, Tgdaya"},"audio_url":"http://ilrdc.tw/grammar/sound/5/10-2-1.mp3"}],[4,{"ori":["Uxe","plnguun","ka","heya."],"gloss":[["uxe","",""],["p-languy-un","",""],["ka","",""],["heya","",""]],"free":["#c 他不可以游泳（，因為今天天氣很冷）。","#n 《賽德克語語法概論》 第十章　否定句結構"],"s_end":true,"iu_a_span":[null,null],"meta":{"type":"GrammarBook","topic":"第十章 否定句結構","language":"賽德克語, Seediq, Tgdaya"},"audio_url":"http://ilrdc.tw/grammar/sound/5/10-2-2.mp3"}],[5,{"ori":["Uxe","naq","mpsdiyan","qpahun","ka","riso","mbserux."],"gloss":[["uxe","",""],["naq","",""],["m-p-sdiyan","",""],["qeepah-un","",""],["ka","",""],["riso","",""],["m-bserux","",""]],"free":["#c 懶惰的年輕人是不會找到工作的。","#n 《賽德克語語法概論》 第十章　否定句結構"],"s_end":true,"iu_a_span":[null,null],"meta":{"type":"GrammarBook","topic":"第十章 否定句結構","language":"賽德克語, Seediq, Tgdaya"},"audio_url":"http://ilrdc.tw/grammar/sound/5/10-2-3.mp3"}],[6,{"ori":["Uxe","psqrahuq","yyahan","na","ka","Dakis."],"gloss":[["uxe","",""],["ps-q-rahuq","",""],["y-eyah-an=na","",""],["ka","",""],["Dakis","",""]],"free":["#c Dakis不可能會遲到。","#n 《賽德克語語法概論》 第十章　否定句結構"],"s_end":true,"iu_a_span":[null,null],"meta":{"type":"GrammarBook","topic":"第十章 否定句結構","language":"賽德克語, Seediq, Tgdaya"},"audio_url":"http://ilrdc.tw/grammar/sound/5/10-2-4.mp3"}],[7,{"ori":["Uxe","qtehur","ka","heya."],"gloss":[["uxe","",""],["qtehur","",""],["ka","",""],["heya","",""]],"free":["#c 他不胖。","#n 《賽德克語語法概論》 第十章　否定句結構"],"s_end":true,"iu_a_span":[null,null],"meta":{"type":"GrammarBook","topic":"第十章 否定句結構","language":"賽德克語, Seediq, Tgdaya"},"audio_url":"http://ilrdc.tw/grammar/sound/5/10-2-5.mp3"}],[8,{"ori":["Ini","beebu","laqi","ka","Dakis."],"gloss":[["ini","",""],["beebu","",""],["laqi","",""],["ka","",""],["Dakis","",""]],"free":["#c （A）Dakis 不（會）打小孩（的）。（B）Dakis 沒有打小孩。","#n 《賽德克語語法概論》 第十章　否定句結構"],"s_end":true,"iu_a_span":[null,null],"meta":{"type":"GrammarBook","topic":"第十章 否定句結構","language":"賽德克語, Seediq, Tgdaya"},"audio_url":"http://ilrdc.tw/grammar/sound/5/10-3-1.mp3"}],[9,{"ori":["Ini","bbei","na","bubu","na","ka","laqi","ga."],"gloss":[["ini","",""],["beebu-i","",""],["na","",""],["bubu=na","",""],["ka","",""],["laqi","",""],["ga","",""]],"free":["#c 那小孩沒有被他媽媽打。","#n 《賽德克語語法概論》 第十章　否定句結構"],"s_end":true,"iu_a_span":[null,null],"meta":{"type":"GrammarBook","topic":"第十章 否定句結構","language":"賽德克語, Seediq, Tgdaya"},"audio_url":"http://ilrdc.tw/grammar/sound/5/10-4-1.mp3"}],[10,{"ori":["Ini","na","hpryani","ido","laqi","ka","bubu."],"gloss":[["ini=na","",""],["pure-ani","",""],["ido","",""],["laqi","",""],["ka","",""],["bubu","",""]],"free":["#c 媽媽沒有為孩子煮飯。","#n 《賽德克語語法概論》 第十章　否定句結構"],"s_end":true,"iu_a_span":[null,null],"meta":{"type":"GrammarBook","topic":"第十章 否定句結構","language":"賽德克語, Seediq, Tgdaya"}}],[11,{"ori":["Ini","qtehur","ka","heya."],"gloss":[["ini","",""],["qtehur","",""],["ka","",""],["heya","",""]],"free":["#c 他不胖。","#n 《賽德克語語法概論》 第十章　否定句結構"],"s_end":true,"iu_a_span":[null,null],"meta":{"type":"GrammarBook","topic":"第十章 否定句結構","language":"賽德克語, Seediq, Tgdaya"},"audio_url":"http://ilrdc.tw/grammar/sound/5/10-6-1.mp3"}],[12,{"ori":["Ani","su","naq","ini","ekan","iyu."],"gloss":[["ani=su","",""],["naq","",""],["ini","",""],["ekan","",""],["iyu","",""]],"free":["#c 你不須吃藥。","#n 《賽德克語語法概論》 第十章　否定句結構"],"s_end":true,"iu_a_span":[null,null],"meta":{"type":"GrammarBook","topic":"第十章 否定句結構","language":"賽德克語, Seediq, Tgdaya"},"audio_url":"http://ilrdc.tw/grammar/sound/5/10-7-1.mp3"}],[13,{"ori":["Naka","su","ini","osa","lmiqu."],"gloss":[["naka=su","",""],["ini","",""],["osa","",""],["lmiqu","",""]],"free":["#c 你不應該去山上（狩獵）。","#n 《賽德克語語法概論》 第十章　否定句結構"],"s_end":true,"iu_a_span":[null,null],"meta":{"type":"GrammarBook","topic":"第十章 否定句結構","language":"賽德克語, Seediq, Tgdaya"},"audio_url":"http://ilrdc.tw/grammar/sound/5/10-7-2.mp3"}],[14,{"ori":["Ani","su","naq","ini","eniq","alang","nii."],"gloss":[["ani=su","",""],["naq","",""],["ini","",""],["eniq","",""],["alang","",""],["nii","",""]],"free":["#c 你不一定要住這個部落。","#n 《賽德克語語法概論》 第十章　否定句結構"],"s_end":true,"iu_a_span":[null,null],"meta":{"type":"GrammarBook","topic":"第十章 否定句結構","language":"賽德克語, Seediq, Tgdaya"},"audio_url":"http://ilrdc.tw/grammar/sound/5/10-7-3.mp3"}],[15,{"ori":["Ani","uxe","yaku","ka","mnekan,","yaku","ka","hliyun","di."],"gloss":[["ani","",""],["uxe","",""],["yaku","",""],["ka","",""],["m<n>ekan,","",""],["yaku","",""],["ka","",""],["hili-un","",""],["di","",""]],"free":["#c 即使不是我吃的，但我就是被誤會。","#n 《賽德克語語法概論》 第十章　否定句結構"],"s_end":true,"iu_a_span":[null,null],"meta":{"type":"GrammarBook","topic":"第十章 否定句結構","language":"賽德克語, Seediq, Tgdaya"},"audio_url":"http://ilrdc.tw/grammar/sound/5/10-8-1.mp3"}],[16,{"ori":["Naka","uxe","heya","ka","seno","na","Temi,","uka","naq","brahan","di."],"gloss":[["naka","",""],["uxe","",""],["heya","",""],["ka","",""],["seno","",""],["na","",""],["Temi,","",""],["uka","",""],["naq","",""],["barah-an","",""],["di","",""]],"free":["#c Temi 的先生（Temi 嫁的）應該不是他，已經沒辦法了。","#n 《賽德克語語法概論》 第十章　否定句結構"],"s_end":true,"iu_a_span":[null,null],"meta":{"type":"GrammarBook","topic":"第十章 否定句結構","language":"賽德克語, Seediq, Tgdaya"},"audio_url":"http://ilrdc.tw/grammar/sound/5/10-8-2.mp3"}],[17,{"ori":["Yaani","uxe","meeyah","ka","Takun","da."],"gloss":[["yaani","",""],["uxe","",""],["me-eyah","",""],["ka","",""],["Takun","",""],["da","",""]],"free":["#c Takun 也許不會來了。","#n 《賽德克語語法概論》 第十章　否定句結構"],"s_end":true,"iu_a_span":[null,null],"meta":{"type":"GrammarBook","topic":"第十章 否定句結構","language":"賽德克語, Seediq, Tgdaya"},"audio_url":"http://ilrdc.tw/grammar/sound/5/10-8-3.mp3"}],[18,{"ori":["Uka","sapah","pyasan","ka","hini."],"gloss":[["uka","",""],["sapah","",""],["pyasan","",""],["ka","",""],["hini","",""]],"free":["#c 這裡沒有學校。","#n 《賽德克語語法概論》 第十章　否定句結構"],"s_end":true,"iu_a_span":[null,null],"meta":{"type":"GrammarBook","topic":"第十章 否定句結構","language":"賽德克語, Seediq, Tgdaya"},"audio_url":"http://ilrdc.tw/grammar/sound/5/10-9-1.mp3"}],[19,{"ori":["Uka","pila","ka","Dakis."],"gloss":[["uka","",""],["pila","",""],["ka","",""],["Dakis","",""]],"free":["#c Dakis沒有錢。","#n 《賽德克語語法概論》 第十章　否定句結構"],"s_end":true,"iu_a_span":[null,null],"meta":{"type":"GrammarBook","topic":"第十章 否定句結構","language":"賽德克語, Seediq, Tgdaya"},"audio_url":"http://ilrdc.tw/grammar/sound/5/10-9-2.mp3"}],[20,{"ori":["Uka","ka","seediq","meeyah."],"gloss":[["uka","",""],["ka","",""],["seediq","",""],["me-eyah.","",""]],"free":["#c 沒有人來。","#n 《賽德克語語法概論》 第十章　否定句結構"],"s_end":true,"iu_a_span":[null,null],"meta":{"type":"GrammarBook","topic":"第十章 否定句結構","language":"賽德克語, Seediq, Tgdaya"},"audio_url":"http://ilrdc.tw/grammar/sound/5/10-9-3.mp3"}],[21,{"ori":["Uka","sapah","na","hii","ka","Pawan."],"gloss":[["uka","",""],["sapah=na","",""],["hii","",""],["ka","",""],["Pawan","",""]],"free":["#c Pawan 在那沒有家。","#n 《賽德克語語法概論》 第十章　否定句結構"],"s_end":true,"iu_a_span":[null,null],"meta":{"type":"GrammarBook","topic":"第十章 否定句結構","language":"賽德克語, Seediq, Tgdaya"},"audio_url":"http://ilrdc.tw/grammar/sound/5/10-9-4.mp3"}],[22,{"ori":["Ini","eniq","nganguc","hii","ka","bubu","mu."],"gloss":[["ini","",""],["eniq","",""],["nganguc","",""],["hii","",""],["ka","",""],["bubu=mu","",""]],"free":["#c 我母親不在外面。","#n 《賽德克語語法概論》 第十章　否定句結構"],"s_end":true,"iu_a_span":[null,null],"meta":{"type":"GrammarBook","topic":"第十章 否定句結構","language":"賽德克語, Seediq, Tgdaya"},"audio_url":"http://ilrdc.tw/grammar/sound/5/10-9-5.mp3"}],[23,{"ori":["Iya","osa","phuling!"],"gloss":[["iya","",""],["osa","",""],["phuling","",""]],"free":["#c 別去狗獵！","#n 《賽德克語語法概論》 第十章　否定句結構"],"s_end":true,"iu_a_span":[null,null],"meta":{"type":"GrammarBook","topic":"第十章 否定句結構","language":"賽德克語, Seediq, Tgdaya"},"audio_url":"http://ilrdc.tw/grammar/sound/5/10-10-1.mp3"}],[24,{"ori":["Iya","lingis!"],"gloss":[["iya","",""],["lingis","",""]],"free":["#c 別哭！","#n 《賽德克語語法概論》 第十章　否定句結構"],"s_end":true,"iu_a_span":[null,null],"meta":{"type":"GrammarBook","topic":"第十章 否定句結構","language":"賽德克語, Seediq, Tgdaya"},"audio_url":"http://ilrdc.tw/grammar/sound/5/10-10-2.mp3"}],[25,{"ori":["Iya","ekan","bunga!"],"gloss":[["iya","",""],["ekan","",""],["bunga","",""]],"free":["#c 別吃地瓜！","#n 《賽德克語語法概論》 第十章　否定句結構"],"s_end":true,"iu_a_span":[null,null],"meta":{"type":"GrammarBook","topic":"第十章 否定句結構","language":"賽德克語, Seediq, Tgdaya"},"audio_url":"http://ilrdc.tw/grammar/sound/5/10-10-3.mp3"}],[26,{"ori":["Iya","puqi","ka","bunga!"],"gloss":[["iya","",""],["puq-i","",""],["ka","",""],["bunga","",""]],"free":["#c 地瓜別吃！","#n 《賽德克語語法概論》 第十章　否定句結構"],"s_end":true,"iu_a_span":[null,null],"meta":{"type":"GrammarBook","topic":"第十章 否定句結構","language":"賽德克語, Seediq, Tgdaya"},"audio_url":"http://ilrdc.tw/grammar/sound/5/10-10-4.mp3"}],[27,{"ori":["Iya","hpryani","ido","ka","laqi","krekan","ga!"],"gloss":[["iya","",""],["pure-ani","",""],["ido","",""],["ka","",""],["laqi","",""],["krekan","",""],["ga","",""]],"free":["#c 別為那不聽話的孩子煮飯！","#n 《賽德克語語法概論》 第十章　否定句結構"],"s_end":true,"iu_a_span":[null,null],"meta":{"type":"GrammarBook","topic":"第十章 否定句結構","language":"賽德克語, Seediq, Tgdaya"},"audio_url":"http://ilrdc.tw/grammar/sound/5/10-10-5.mp3"}],[28,{"ori":["Maha","su","Taipe?","Uxe.","Uxe","ku","maha."],"gloss":[["maha=su","",""],["Taipe","",""],["uxe","",""],["uxe=ku","",""],["maha","",""]],"free":["#c 問：你要去台北嗎？沒有。我不去。","#n 《賽德克語語法概論》 第十章　否定句結構"],"s_end":true,"iu_a_span":[null,null],"meta":{"type":"GrammarBook","topic":"第十章 否定句結構","language":"賽德克語, Seediq, Tgdaya"},"audio_url":"http://ilrdc.tw/grammar/sound/5/10-11-1.mp3"}],[29,{"ori":["Ga","sapah","bubu","su?","Uka","hiya."],"gloss":[["ga","",""],["sapah","",""],["bubu=su","",""],["uka","",""],["hiya","",""]],"free":["#c 你媽媽在家嗎？（在外頭遇到該媽媽的小孩時問的）不在那裡。","#n 《賽德克語語法概論》 第十章　否定句結構"],"s_end":true,"iu_a_span":[null,null],"meta":{"type":"GrammarBook","topic":"第十章 否定句結構","language":"賽德克語, Seediq, Tgdaya"},"audio_url":"http://ilrdc.tw/grammar/sound/5/10-11-2.mp3"}],[30,{"ori":["Ini","na","ba","ttlami","mimah","sino","ka","heya."],"gloss":[["ini=na","",""],["ba","",""],["t-tlami","",""],["m-imah","",""],["sino","",""],["ka","",""],["heya","",""]],"free":["#c 他從未嘗試著要喝酒。","#n 《賽德克語語法概論》 第十章　否定句結構"],"s_end":true,"iu_a_span":[null,null],"meta":{"type":"GrammarBook","topic":"第十章 否定句結構","language":"賽德克語, Seediq, Tgdaya"},"audio_url":"http://ilrdc.tw/grammar/sound/5/10-12-1.mp3"}],[31,{"ori":["Ini","riyung","eyah","sapah","ka","heya."],"gloss":[["ini","",""],["riyung","",""],["eyah","",""],["sapah","",""],["ka","",""],["heya","",""]],"free":["#c 他不常回家。","#n 《賽德克語語法概論》 第十章　否定句結構"],"s_end":true,"iu_a_span":[null,null],"meta":{"type":"GrammarBook","topic":"第十章 否定句結構","language":"賽德克語, Seediq, Tgdaya"},"audio_url":"http://ilrdc.tw/grammar/sound/5/10-12-2.mp3"}],[32,{"ori":["Uxe","uka","pila","ka","heya."],"gloss":[["uxe","",""],["uka","",""],["pila","",""],["ka","",""],["heya","",""]],"free":["#c 他不是沒有錢。","#n 《賽德克語語法概論》 第十章　否定句結構"],"s_end":true,"iu_a_span":[null,null],"meta":{"type":"GrammarBook","topic":"第十章 否定句結構","language":"賽德克語, Seediq, Tgdaya"},"audio_url":"http://ilrdc.tw/grammar/sound/5/10-13-1.mp3"}],[33,{"ori":["Uxe","bale","ba","ka","ini","ku","skuxul","heya."],"gloss":[["uxe","",""],["bale","",""],["ba","",""],["ka","",""],["ini=ku","",""],["s-kuxul","",""],["heya","",""]],"free":["#c 我不喜歡他不是真的。","#n 《賽德克語語法概論》 第十章　否定句結構"],"s_end":true,"iu_a_span":[null,null],"meta":{"type":"GrammarBook","topic":"第十章 否定句結構","language":"賽德克語, Seediq, Tgdaya"},"audio_url":"http://ilrdc.tw/grammar/sound/5/10-13-2.mp3"}],[34,{"ori":["Uxe","kesun","ini","mkmosa","phuling","ka","Dakis,","ga","naq","muuwic","han."],"gloss":[["uxe","",""],["kesa-un","",""],["ini","",""],["mk-m-osa","",""],["phuling","",""],["ka","",""],["Dakis","",""],["ga","",""],["naq","",""],["muuwic","",""],["han","",""]],"free":["#c Dakis不是不想去打獵，只是他有點累。","#n 《賽德克語語法概論》 第十章　否定句結構"],"s_end":true,"iu_a_span":[null,null],"meta":{"type":"GrammarBook","topic":"第十章 否定句結構","language":"賽德克語, Seediq, Tgdaya"},"audio_url":"http://ilrdc.tw/grammar/sound/5/10-13-3.mp3"}]],"meta":{"type":"GrammarBook","topic":"第十章 否定句結構","language":"賽德克語, Seediq, Tgdaya"}}